_mis_finder_core.cpython-310-x86_64-linux-gnu.so
mis_finder/__init__.py
mis_finder/_core/mis.c
mis_finder/_core/mis_impl.c
mis_finder/_core/parse_numpy.c
mis_finder.libs/libgomp-a34b3233.so.1.0.0
mis_finder-0.2.0.dist-info/METADATA
mis_finder-0.2.0.dist-info/top_level.txt
mis_finder-0.2.0.dist-info/WHEEL
mis_finder-0.2.0.dist-info/RECORD
mis_finder-0.2.0.dist-info/LICENSE
